LICENSE
README.md
setup.cfg
setup.py
carefree_cv.egg-info/PKG-INFO
carefree_cv.egg-info/SOURCES.txt
carefree_cv.egg-info/dependency_links.txt
carefree_cv.egg-info/requires.txt
carefree_cv.egg-info/top_level.txt
cfcv/__init__.py
cfcv/legacy/__init__.py
cfcv/legacy/shape.py
cfcv/legacy/utils.py
cfcv/legacy/processor/__init__.py
cfcv/legacy/processor/core.py
cfcv/misc/__init__.py
cfcv/misc/toolkit.py