Metadata-Version: 2.1
Name: carefree-cv
Version: 0.1.1
Summary: Some commonly used computer vision functions and modules
Home-page: https://github.com/carefree0910/carefree-cv
Download-URL: https://github.com/carefree0910/carefree-cv/archive/v0.1.1.tar.gz
Author: carefree0910
Author-email: syameimaru.saki@gmail.com
Keywords: python computer-vision
License-File: LICENSE
